{"stats":{"minecraft:custom":{"minecraft:jump":49,"minecraft:interact_with_brewingstand":3,"minecraft:time_since_rest":3821,"minecraft:leave_game":1,"minecraft:sprint_one_cm":1528,"minecraft:play_time":3821,"minecraft:time_since_death":3821,"minecraft:walk_one_cm":1810,"minecraft:total_world_time":4000,"minecraft:drop":1,"minecraft:fly_one_cm":6825},"minecraft:picked_up":{"mdi:glowing_mushroom":1},"minecraft:used":{"minecraft:brewing_stand":1,"minecraft:potion":1,"mdi:glowing_mushroom":2,"mdi:diolite_block":1},"minecraft:dropped":{"mdi:glowing_mushroom":1}},"DataVersion":2865}